trials/__init__.py
trials/buildspec.py
trials/createdefine.py
trials-0.0.1.dist-info/LICENSE
trials-0.0.1.dist-info/METADATA
trials-0.0.1.dist-info/WHEEL
trials-0.0.1.dist-info/top_level.txt
trials-0.0.1.dist-info/RECORD
