Metadata-Version: 2.1
Name: trials
Version: 0.0.1
Summary: A Package designed to create a regulatory compliant define.XML document
Home-page: https://github.com/kevinjacksonm/trials
Author: Kevin Miller & Larry Sleeper
Author-email: kevinjacksonmiller@gmail.com
License: UNKNOWN
Platform: UNKNOWN
Classifier: Programming Language :: Python :: 3
Classifier: License :: OSI Approved :: MIT License
Classifier: Operating System :: OS Independent
Requires-Python: >=3.4
